app_min.py
nano_slug-0.1.1.dist-info/licenses/LICENSE
nano_slug-0.1.1.dist-info/METADATA
nano_slug-0.1.1.dist-info/WHEEL
nano_slug-0.1.1.dist-info/entry_points.txt
nano_slug-0.1.1.dist-info/top_level.txt
nano_slug-0.1.1.dist-info/RECORD
