Metadata-Version: 2.4
Name: nano-slug
Version: 0.1.1
Summary: Tiny text → URL slug converter in ~1KB (zero deps)
Author: ozgunlu
License: MIT
Project-URL: Homepage, https://github.com/ozgunlu/nano-slug
Project-URL: Issues, https://github.com/ozgunlu/nano-slug/issues
Requires-Python: >=3.8
License-File: LICENSE
Dynamic: license-file
